{"Sr_No": "0714", "Accession_No": "0308", "Title_devanagari": "\u0917\u0923\u0947\u0936\u0917\u0940\u0924\u093e", "Title_hk": "gaNezagItA", "Title_slp1": "gaReSagItA", "Title_itrans": "gaNeshagItA", "Title_iast": "ga\u1e47e\u015bag\u012bt\u0101", "Title_kolkata": "ga\u1e47\u0113\u015bag\u012bt\u0101", "Title_velthuis": "ga.ne\"sagiitaa", "Title_optitrans": "gaNeshagItA", "Title_bengali": "\u0997\u09a3\u09c7\u09b6\u0997\u09c0\u09a4\u09be", "Title_gujarati": "\u0a97\u0aa3\u0ac7\u0ab6\u0a97\u0ac0\u0aa4\u0abe", "Title_kannada": "\u0c97\u0ca3\u0cc7\u0cb6\u0c97\u0cc0\u0ca4\u0cbe", "Title_malayalam": "\u0d17\u0d23\u0d47\u0d36\u0d17\u0d40\u0d24\u0d3e", "Title_oriya": "\u0b17\u0b23\u0b47\u0b36\u0b17\u0b40\u0b24\u0b3e", "Title_tamil": "\u0b95\u0ba3\u0bc7\u0bb6\u0b95\u0bc0\u0ba4\u0bbe", "Title_telugu": "\u0c17\u0c23\u0c47\u0c36\u0c17\u0c40\u0c24\u0c3e", "Title_keyword": "ganeshagita", "Author_devanagari": "--", "Author_hk": "--", "Author_slp1": "--", "Author_itrans": "--", "Author_iast": "--", "Author_kolkata": "--", "Author_velthuis": "--", "Author_optitrans": "--", "Author_bengali": "--", "Author_gujarati": "--", "Author_kannada": "--", "Author_malayalam": "--", "Author_oriya": "--", "Author_tamil": "--", "Author_telugu": "--", "Author_keyword": "--", "Commentator_devanagari": "--", "Commentator_hk": "--", "Commentator_slp1": "--", "Commentator_itrans": "--", "Commentator_iast": "--", "Commentator_kolkata": "--", "Commentator_velthuis": "--", "Commentator_optitrans": "--", "Commentator_bengali": "--", "Commentator_gujarati": "--", "Commentator_kannada": "--", "Commentator_malayalam": "--", "Commentator_oriya": "--", "Commentator_tamil": "--", "Commentator_telugu": "--", "Commentator_keyword": "--", "Material": "Paper", "Script": "DN", "aSize": "5.5\"x3.2\"", "bSize": "3.8\"x2\"", "Line": "6", "Letters": "15", "Folios": "87", "Scribe_devanagari": "--", "Scribe_hk": "--", "Scribe_slp1": "--", "Scribe_itrans": "--", "Scribe_iast": "--", "Scribe_kolkata": "--", "Scribe_velthuis": "--", "Scribe_optitrans": "--", "Scribe_bengali": "--", "Scribe_gujarati": "--", "Scribe_kannada": "--", "Scribe_malayalam": "--", "Scribe_oriya": "--", "Scribe_tamil": "--", "Scribe_telugu": "--", "Scribe_keyword": "--", "Condition": "Good", "Age_of_MS": "--", "Additional_remarks": "Foll. 1-24 missing. Begins abruptly.", "Subject": "The Purana L. & R.", "identifier": "ganeshagita-CGV-PSS-0714-0308", "mediatype": "texts", "collection": "opensource", "creator": "Chunilal Gandhi Vidyabhavan Surat", "description": "Pandit Shivadatta Shukla collection of manuscripts of Chunilal Gandhi Vidyabhavan, Surat.", "language": "san", "email": "cgvidyabhavan@gmail.com"}