{"Sr_No": "0235", "Accession_No": "0652", "Title_devanagari": "\u0910\u0924\u0930\u0947\u092f \u0909\u092a\u0928\u093f\u0937\u0926\u094d", "Title_hk": "aitareya upaniSad", "Title_slp1": "Etareya upanizad", "Title_itrans": "aitareya upaniShad", "Title_iast": "aitareya upani\u1e63ad", "Title_kolkata": "aitar\u0113ya upani\u1e63ad", "Title_velthuis": "aitareya upani.sad", "Title_optitrans": "aitareya upaniShad", "Title_bengali": "\u0990\u09a4\u09b0\u09c7\u09af \u0989\u09aa\u09a8\u09bf\u09b7\u09a6\u09cd", "Title_gujarati": "\u0a90\u0aa4\u0ab0\u0ac7\u0aaf \u0a89\u0aaa\u0aa8\u0abf\u0ab7\u0aa6\u0acd", "Title_kannada": "\u0c90\u0ca4\u0cb0\u0cc7\u0caf \u0c89\u0caa\u0ca8\u0cbf\u0cb7\u0ca6\u0ccd", "Title_malayalam": "\u0d10\u0d24\u0d30\u0d47\u0d2f \u0d09\u0d2a\u0d28\u0d3f\u0d37\u0d26\u0d4d", "Title_oriya": "\u0b10\u0b24\u0b30\u0b47\u0b2f \u0b09\u0b2a\u0b28\u0b3f\u0b37\u0b26\u0b4d", "Title_tamil": "\u0b90\u0ba4\u0bb0\u0bc7\u0baf \u0b89\u0baa\u0ba8\u0bbf\u0bb7\u0ba4\u0bcd", "Title_telugu": "\u0c10\u0c24\u0c30\u0c47\u0c2f \u0c09\u0c2a\u0c28\u0c3f\u0c37\u0c26\u0c4d", "Title_keyword": "aitareya upanishad", "Author_devanagari": "--", "Author_hk": "--", "Author_slp1": "--", "Author_itrans": "--", "Author_iast": "--", "Author_kolkata": "--", "Author_velthuis": "--", "Author_optitrans": "--", "Author_bengali": "--", "Author_gujarati": "--", "Author_kannada": "--", "Author_malayalam": "--", "Author_oriya": "--", "Author_tamil": "--", "Author_telugu": "--", "Author_keyword": "--", "Commentator_devanagari": "--", "Commentator_hk": "--", "Commentator_slp1": "--", "Commentator_itrans": "--", "Commentator_iast": "--", "Commentator_kolkata": "--", "Commentator_velthuis": "--", "Commentator_optitrans": "--", "Commentator_bengali": "--", "Commentator_gujarati": "--", "Commentator_kannada": "--", "Commentator_malayalam": "--", "Commentator_oriya": "--", "Commentator_tamil": "--", "Commentator_telugu": "--", "Commentator_keyword": "--", "Material": "Paper", "Script": "DN", "aSize": "10.8\"x4.1\"", "bSize": "8\"x2.3\"", "Line": "11", "Letters": "42", "Folios": "31", "Scribe_devanagari": "\u0926\u093e\u092e\u094b\u0926\u0930", "Scribe_hk": "dAmodara", "Scribe_slp1": "dAmodara", "Scribe_itrans": "dAmodara", "Scribe_iast": "d\u0101modara", "Scribe_kolkata": "d\u0101m\u014ddara", "Scribe_velthuis": "daamodara", "Scribe_optitrans": "dAmodara", "Scribe_bengali": "\u09a6\u09be\u09ae\u09cb\u09a6\u09b0", "Scribe_gujarati": "\u0aa6\u0abe\u0aae\u0acb\u0aa6\u0ab0", "Scribe_kannada": "\u0ca6\u0cbe\u0cae\u0ccb\u0ca6\u0cb0", "Scribe_malayalam": "\u0d26\u0d3e\u0d2e\u0d4b\u0d26\u0d30", "Scribe_oriya": "\u0b26\u0b3e\u0b2e\u0b4b\u0b26\u0b30", "Scribe_tamil": "\u0ba4\u0bbe\u0bae\u0bcb\u0ba4\u0bb0", "Scribe_telugu": "\u0c26\u0c3e\u0c2e\u0c4b\u0c26\u0c30", "Scribe_keyword": "damodara", "Condition": "Good", "Age_of_MS": "shaka 1666", "Additional_remarks": "--", "Subject": "Vedic & Ritual", "identifier": "aitareya_upanishad-CGV-PSS-0235-0652", "mediatype": "texts", "collection": "opensource", "creator": "Chunilal Gandhi Vidyabhavan Surat", "description": "Pandit Shivadatta Shukla collection of manuscripts of Chunilal Gandhi Vidyabhavan, Surat.", "language": "san", "email": "cgvidyabhavan@gmail.com"}