{"Sr_No": "1149", "Accession_No": "0969", "Title_devanagari": "\u092d\u0948\u0930\u0935\u0938\u093e\u0927\u0928\u093e", "Title_hk": "bhairavasAdhanA", "Title_slp1": "BEravasADanA", "Title_itrans": "bhairavasAdhanA", "Title_iast": "bhairavas\u0101dhan\u0101", "Title_kolkata": "bhairavas\u0101dhan\u0101", "Title_velthuis": "bhairavasaadhanaa", "Title_optitrans": "bhairavasAdhanA", "Title_bengali": "\u09ad\u09c8\u09b0\u09ac\u09b8\u09be\u09a7\u09a8\u09be", "Title_gujarati": "\u0aad\u0ac8\u0ab0\u0ab5\u0ab8\u0abe\u0aa7\u0aa8\u0abe", "Title_kannada": "\u0cad\u0cc8\u0cb0\u0cb5\u0cb8\u0cbe\u0ca7\u0ca8\u0cbe", "Title_malayalam": "\u0d2d\u0d48\u0d30\u0d35\u0d38\u0d3e\u0d27\u0d28\u0d3e", "Title_oriya": "\u0b2d\u0b48\u0b30\u0b35\u0b38\u0b3e\u0b27\u0b28\u0b3e", "Title_tamil": "\u0baa\u0bc8\u0bb0\u0bb5\u0bb8\u0bbe\u0ba4\u0ba8\u0bbe", "Title_telugu": "\u0c2d\u0c48\u0c30\u0c35\u0c38\u0c3e\u0c27\u0c28\u0c3e", "Title_keyword": "bhairavasadhana", "Author_devanagari": "--", "Author_hk": "--", "Author_slp1": "--", "Author_itrans": "--", "Author_iast": "--", "Author_kolkata": "--", "Author_velthuis": "--", "Author_optitrans": "--", "Author_bengali": "--", "Author_gujarati": "--", "Author_kannada": "--", "Author_malayalam": "--", "Author_oriya": "--", "Author_tamil": "--", "Author_telugu": "--", "Author_keyword": "--", "Commentator_devanagari": "--", "Commentator_hk": "--", "Commentator_slp1": "--", "Commentator_itrans": "--", "Commentator_iast": "--", "Commentator_kolkata": "--", "Commentator_velthuis": "--", "Commentator_optitrans": "--", "Commentator_bengali": "--", "Commentator_gujarati": "--", "Commentator_kannada": "--", "Commentator_malayalam": "--", "Commentator_oriya": "--", "Commentator_tamil": "--", "Commentator_telugu": "--", "Commentator_keyword": "--", "Material": "Paper", "Script": "DN", "aSize": "7.6\"x4.4\"", "bSize": "6.2\"x2.8\"", "Line": "9", "Letters": "26", "Folios": "5", "Scribe_devanagari": "--", "Scribe_hk": "--", "Scribe_slp1": "--", "Scribe_itrans": "--", "Scribe_iast": "--", "Scribe_kolkata": "--", "Scribe_velthuis": "--", "Scribe_optitrans": "--", "Scribe_bengali": "--", "Scribe_gujarati": "--", "Scribe_kannada": "--", "Scribe_malayalam": "--", "Scribe_oriya": "--", "Scribe_tamil": "--", "Scribe_telugu": "--", "Scribe_keyword": "--", "Condition": "Good", "Age_of_MS": "--", "Additional_remarks": "Complete. Folios are not paginated, torn and worm-eaten.", "Subject": "Tantrik Lit. And Ritual", "identifier": "bhairavasadhana-CGV-PSS-1149-0969", "mediatype": "texts", "collection": "opensource", "creator": "Chunilal Gandhi Vidyabhavan Surat", "description": "Pandit Shivadatta Shukla collection of manuscripts of Chunilal Gandhi Vidyabhavan, Surat.", "language": "san", "email": "cgvidyabhavan@gmail.com"}