{"Sr_No": "1226", "Accession_No": "1211", "Title_devanagari": "\u0935\u093f\u092d\u0942\u0924\u093f\u0927\u093e\u0930\u0923\u092e\u0939\u093e\u092e\u0928\u094d\u0924\u094d\u0930", "Title_hk": "vibhUtidhAraNamahAmantra", "Title_slp1": "viBUtiDAraRamahAmantra", "Title_itrans": "vibhUtidhAraNamahAmantra", "Title_iast": "vibh\u016btidh\u0101ra\u1e47amah\u0101mantra", "Title_kolkata": "vibh\u016btidh\u0101ra\u1e47amah\u0101mantra", "Title_velthuis": "vibhuutidhaara.namahaamantra", "Title_optitrans": "vibhUtidhAraNamahAmantra", "Title_bengali": "\u09ac\u09bf\u09ad\u09c2\u09a4\u09bf\u09a7\u09be\u09b0\u09a3\u09ae\u09b9\u09be\u09ae\u09a8\u09cd\u09a4\u09cd\u09b0", "Title_gujarati": "\u0ab5\u0abf\u0aad\u0ac2\u0aa4\u0abf\u0aa7\u0abe\u0ab0\u0aa3\u0aae\u0ab9\u0abe\u0aae\u0aa8\u0acd\u0aa4\u0acd\u0ab0", "Title_kannada": "\u0cb5\u0cbf\u0cad\u0cc2\u0ca4\u0cbf\u0ca7\u0cbe\u0cb0\u0ca3\u0cae\u0cb9\u0cbe\u0cae\u0ca8\u0ccd\u0ca4\u0ccd\u0cb0", "Title_malayalam": "\u0d35\u0d3f\u0d2d\u0d42\u0d24\u0d3f\u0d27\u0d3e\u0d30\u0d23\u0d2e\u0d39\u0d3e\u0d2e\u0d28\u0d4d\u0d24\u0d4d\u0d30", "Title_oriya": "\u0b35\u0b3f\u0b2d\u0b42\u0b24\u0b3f\u0b27\u0b3e\u0b30\u0b23\u0b2e\u0b39\u0b3e\u0b2e\u0b28\u0b4d\u0b24\u0b4d\u0b30", "Title_tamil": "\u0bb5\u0bbf\u0baa\u0bc2\u0ba4\u0bbf\u0ba4\u0bbe\u0bb0\u0ba3\u0bae\u0bb9\u0bbe\u0bae\u0ba8\u0bcd\u0ba4\u0bcd\u0bb0", "Title_telugu": "\u0c35\u0c3f\u0c2d\u0c42\u0c24\u0c3f\u0c27\u0c3e\u0c30\u0c23\u0c2e\u0c39\u0c3e\u0c2e\u0c28\u0c4d\u0c24\u0c4d\u0c30", "Title_keyword": "vibhutidharanamahamantra", "Author_devanagari": "--", "Author_hk": "--", "Author_slp1": "--", "Author_itrans": "--", "Author_iast": "--", "Author_kolkata": "--", "Author_velthuis": "--", "Author_optitrans": "--", "Author_bengali": "--", "Author_gujarati": "--", "Author_kannada": "--", "Author_malayalam": "--", "Author_oriya": "--", "Author_tamil": "--", "Author_telugu": "--", "Author_keyword": "--", "Commentator_devanagari": "--", "Commentator_hk": "--", "Commentator_slp1": "--", "Commentator_itrans": "--", "Commentator_iast": "--", "Commentator_kolkata": "--", "Commentator_velthuis": "--", "Commentator_optitrans": "--", "Commentator_bengali": "--", "Commentator_gujarati": "--", "Commentator_kannada": "--", "Commentator_malayalam": "--", "Commentator_oriya": "--", "Commentator_tamil": "--", "Commentator_telugu": "--", "Commentator_keyword": "--", "Material": "Paper", "Script": "DN", "aSize": "7.9\"x3\"", "bSize": "7\"x2.3\"", "Line": "10", "Letters": "38", "Folios": "2", "Scribe_devanagari": "--", "Scribe_hk": "--", "Scribe_slp1": "--", "Scribe_itrans": "--", "Scribe_iast": "--", "Scribe_kolkata": "--", "Scribe_velthuis": "--", "Scribe_optitrans": "--", "Scribe_bengali": "--", "Scribe_gujarati": "--", "Scribe_kannada": "--", "Scribe_malayalam": "--", "Scribe_oriya": "--", "Scribe_tamil": "--", "Scribe_telugu": "--", "Scribe_keyword": "--", "Condition": "Good", "Age_of_MS": "--", "Additional_remarks": "Complete.", "Subject": "Tantrik Lit. And Ritual", "identifier": "vibhutidharanamahamantra-CGV-PSS-1226-1211", "mediatype": "texts", "collection": "opensource", "creator": "Chunilal Gandhi Vidyabhavan Surat", "description": "Pandit Shivadatta Shukla collection of manuscripts of Chunilal Gandhi Vidyabhavan, Surat.", "language": "san", "email": "cgvidyabhavan@gmail.com"}