{"Accession_No": "SDPB0211", "Subject": "Jyotisha", "Title_devanagari": "\u092a\u093e\u0936\u0915\u093e\u0935\u0932\u0940", "Title_hk": "pAzakAvalI", "Title_slp1": "pASakAvalI", "Title_itrans": "pAshakAvalI", "Title_iast": "p\u0101\u015bak\u0101val\u012b", "Title_kolkata": "p\u0101\u015bak\u0101val\u012b", "Title_velthuis": "paa\"sakaavalii", "Title_optitrans": "pAshakAvalI", "Title_bengali": "\u09aa\u09be\u09b6\u0995\u09be\u09ac\u09b2\u09c0", "Title_gujarati": "\u0aaa\u0abe\u0ab6\u0a95\u0abe\u0ab5\u0ab2\u0ac0", "Title_kannada": "\u0caa\u0cbe\u0cb6\u0c95\u0cbe\u0cb5\u0cb2\u0cc0", "Title_malayalam": "\u0d2a\u0d3e\u0d36\u0d15\u0d3e\u0d35\u0d32\u0d40", "Title_oriya": "\u0b2a\u0b3e\u0b36\u0b15\u0b3e\u0b35\u0b32\u0b40", "Title_tamil": "\u0baa\u0bbe\u0bb6\u0b95\u0bbe\u0bb5\u0bb2\u0bc0", "Title_telugu": "\u0c2a\u0c3e\u0c36\u0c15\u0c3e\u0c35\u0c32\u0c40", "Title_keyword": "pashakavali", "Author_devanagari": "\u0917\u0930\u094d\u0917", "Author_hk": "garga", "Author_slp1": "garga", "Author_itrans": "garga", "Author_iast": "garga", "Author_kolkata": "garga", "Author_velthuis": "garga", "Author_optitrans": "garga", "Author_bengali": "\u0997\u09b0\u09cd\u0997", "Author_gujarati": "\u0a97\u0ab0\u0acd\u0a97", "Author_kannada": "\u0c97\u0cb0\u0ccd\u0c97", "Author_malayalam": "\u0d17\u0d30\u0d4d\u0d17", "Author_oriya": "\u0b17\u0b30\u0b4d\u0b17", "Author_tamil": "\u0b95\u0bb0\u0bcd\u0b95", "Author_telugu": "\u0c17\u0c30\u0c4d\u0c17", "Author_keyword": "garga", "Scribe_devanagari": "", "Scribe_hk": "", "Scribe_slp1": "", "Scribe_itrans": "", "Scribe_iast": "", "Scribe_kolkata": "", "Scribe_velthuis": "", "Scribe_optitrans": "", "Scribe_bengali": "", "Scribe_gujarati": "", "Scribe_kannada": "", "Scribe_malayalam": "", "Scribe_oriya": "", "Scribe_tamil": "", "Scribe_telugu": "", "Scribe_keyword": "", "Date_of_work": "", "Date_of_MS": "V.S. 1667", "Place_of_work": "", "Place_of_MS": "", "Size": "8.1\"x3\"", "Folios": "14", "Script": "Devanagari", "Additional_remarks": "Folio 3 is missing.", "Observations": "", "identifier": "pashakavali-CGV-SDPB-0211", "mediatype": "texts", "collection": "opensource", "creator": "Chunilal Gandhi Vidyabhavan Surat", "description": "Shastri Dinamanishankara Pustaka Bhandara (SDPB) collection of manuscripts of Chunilal Gandhi Vidyabhavan, Surat.", "language": "san", "email": "cgvidyabhavan@gmail.com"}